GormZhongwenWendang/README.md
GormZhongwenWendang/__init__.py
GormZhongwenWendang/__main__.py
GormZhongwenWendang/file.epub
GormZhongwenWendang/index.html
GormZhongwenWendang/css/__init__.py
GormZhongwenWendang/css/annotations.css
GormZhongwenWendang/css/main.css
GormZhongwenWendang/css/normalize.css
GormZhongwenWendang/css/popup.css
GormZhongwenWendang/font/__init__.py
GormZhongwenWendang/font/fontello.eot
GormZhongwenWendang/font/fontello.svg
GormZhongwenWendang/font/fontello.ttf
GormZhongwenWendang/font/fontello.woff
GormZhongwenWendang/img/__init__.py
GormZhongwenWendang/img/annotator-glyph-sprite.png
GormZhongwenWendang/img/annotator-icon-sprite.png
GormZhongwenWendang/img/apple-touch-icon.png
GormZhongwenWendang/img/cancelfullscreen.png
GormZhongwenWendang/img/close.png
GormZhongwenWendang/img/fullscreen.png
GormZhongwenWendang/img/loader.gif
GormZhongwenWendang/img/menu-icon.png
GormZhongwenWendang/img/save.png
GormZhongwenWendang/img/saved.png
GormZhongwenWendang/img/settings-s.png
GormZhongwenWendang/img/settings.png
GormZhongwenWendang/img/star.png
GormZhongwenWendang/js/__init__.py
GormZhongwenWendang/js/epub.js
GormZhongwenWendang/js/epub.min.js
GormZhongwenWendang/js/epub.min.map
GormZhongwenWendang/js/hooks.min.js
GormZhongwenWendang/js/hooks.min.map
GormZhongwenWendang/js/reader.js
GormZhongwenWendang/js/reader.js.map
GormZhongwenWendang/js/reader.min.js
GormZhongwenWendang/js/reader.min.map
GormZhongwenWendang/js/hooks/__init__.py
GormZhongwenWendang/js/hooks/extensions/__init__.py
GormZhongwenWendang/js/hooks/extensions/highlight.js
GormZhongwenWendang/js/libs/__init__.py
GormZhongwenWendang/js/libs/jquery.min.js
GormZhongwenWendang/js/libs/localforage.min.js
GormZhongwenWendang/js/libs/screenfull.js
GormZhongwenWendang/js/libs/screenfull.min.js
GormZhongwenWendang/js/libs/zip.min.js
GormZhongwenWendang/js/plugins/__init__.py
GormZhongwenWendang/js/plugins/hypothesis.js
GormZhongwenWendang/js/plugins/search.js
gorm_zhongwen_wendang-2024.3.5.0.dist-info/METADATA
gorm_zhongwen_wendang-2024.3.5.0.dist-info/WHEEL
gorm_zhongwen_wendang-2024.3.5.0.dist-info/entry_points.txt
gorm_zhongwen_wendang-2024.3.5.0.dist-info/top_level.txt
gorm_zhongwen_wendang-2024.3.5.0.dist-info/RECORD
